{
  "train_set_before_training": 0.504,
  "global_step": 502,
  "average_loss": 0.1010835254008314,
  "log_history": [
    {
      "learning_rate": 9.00398406374502e-06,
      "loss_steps": 0.41909258663654325,
      "epoch": 1,
      "step": 50
    },
    {
      "learning_rate": 8.00796812749004e-06,
      "loss_steps": 0.15628060922026635,
      "epoch": 1,
      "step": 100
    },
    {
      "learning_rate": 7.011952191235061e-06,
      "loss_steps": 0.09232302762567997,
      "epoch": 1,
      "step": 150
    },
    {
      "learning_rate": 6.0159362549800805e-06,
      "loss_steps": 0.06468884944915772,
      "epoch": 1,
      "step": 200
    },
    {
      "learning_rate": 5.0199203187251e-06,
      "loss_steps": 0.060269748270511625,
      "epoch": 1,
      "step": 250
    },
    {
      "learning_rate": 4.02390438247012e-06,
      "loss_steps": 0.047047019153833386,
      "epoch": 1,
      "step": 300
    },
    {
      "learning_rate": 3.0278884462151397e-06,
      "loss_steps": 0.050241127870976926,
      "epoch": 1,
      "step": 350
    },
    {
      "learning_rate": 2.03187250996016e-06,
      "loss_steps": 0.0443308387324214,
      "epoch": 1,
      "step": 400
    },
    {
      "learning_rate": 1.0358565737051795e-06,
      "loss_steps": 0.03967876374721527,
      "epoch": 1,
      "step": 450
    },
    {
      "learning_rate": 3.984063745019921e-08,
      "loss_steps": 0.03922160655260086,
      "epoch": 1,
      "step": 500
    },
    {
      "learning_rate": 0.0,
      "loss": 0.1010835254008314,
      "epoch": 1,
      "step": 502,
      "eval_acc": 0.7524401064773736,
      "eval_accuracy": 0.7524401064773736,
      "eval_f1": 0.7787470261697066,
      "eval_precision": 0.7039426523297491,
      "eval_recall": 0.8713398402839396,
      "eval_f_beta_2.0": 0.8317804506183296,
      "eval_f_beta_0.5": 0.7320709706277024,
      "eval_loss": 0.984983907752778
    }
  ],
  "train_set_after_training": {
    "acc": 0.8005,
    "accuracy": 0.8005,
    "f1": 0.8247694334650857,
    "precision": 0.7399527186761229,
    "recall": 0.9315476190476191,
    "f_beta_2.0": 0.8856819468024901,
    "f_beta_0.5": 0.7716962524654832
  },
  "test_set_after_training": {
    "acc": 0.7524401064773736,
    "accuracy": 0.7524401064773736,
    "f1": 0.7787470261697066,
    "precision": 0.7039426523297491,
    "recall": 0.8713398402839396,
    "f_beta_2.0": 0.8317804506183296,
    "f_beta_0.5": 0.7320709706277024
  }
}